github_tracker/__init__.py
github_tracker/github_trending.py
github_tracker-0.0.1.dist-info/METADATA
github_tracker-0.0.1.dist-info/WHEEL
github_tracker-0.0.1.dist-info/top_level.txt
github_tracker-0.0.1.dist-info/RECORD
