Metadata-Version: 2.4
Name: github-tracker
Version: 0.0.1
Summary: A tool for tracking github trends and repositories.
Project-URL: Homepage, https://github.com/monkitect/github_tracker
Project-URL: Repository, https://github.com/monkitect/github_tracker
Project-URL: Issues, https://github.com/monkitect/github_tracker/issues
Requires-Dist: requests
Requires-Dist: beautifulsoup4
